omnis/__init__.py
omnis/cli.py
omnis/client.py
omnis/tenants.py
omnis_py-0.2.3.dist-info/METADATA
omnis_py-0.2.3.dist-info/WHEEL
omnis_py-0.2.3.dist-info/entry_points.txt
omnis_py-0.2.3.dist-info/RECORD
